odoo/addons/stock_lot_product_qty_search/README.rst
odoo/addons/stock_lot_product_qty_search/__init__.py
odoo/addons/stock_lot_product_qty_search/__manifest__.py
odoo/addons/stock_lot_product_qty_search/i18n/it.po
odoo/addons/stock_lot_product_qty_search/i18n/stock_lot_product_qty_search.pot
odoo/addons/stock_lot_product_qty_search/models/__init__.py
odoo/addons/stock_lot_product_qty_search/models/stock_production_lot.py
odoo/addons/stock_lot_product_qty_search/readme/CONTRIBUTORS.rst
odoo/addons/stock_lot_product_qty_search/readme/DESCRIPTION.rst
odoo/addons/stock_lot_product_qty_search/readme/ROADMAP.rst
odoo/addons/stock_lot_product_qty_search/static/description/icon.png
odoo/addons/stock_lot_product_qty_search/static/description/index.html
odoo/addons/stock_lot_product_qty_search/tests/__init__.py
odoo/addons/stock_lot_product_qty_search/tests/test_search_lot_product_qty.py
odoo/addons/stock_lot_product_qty_search/views/stock_production_lot.xml
odoo_addon_stock_lot_product_qty_search-15.0.1.0.0.6.dist-info/METADATA
odoo_addon_stock_lot_product_qty_search-15.0.1.0.0.6.dist-info/WHEEL
odoo_addon_stock_lot_product_qty_search-15.0.1.0.0.6.dist-info/top_level.txt
odoo_addon_stock_lot_product_qty_search-15.0.1.0.0.6.dist-info/RECORD
