Metadata-Version: 2.1
Name: odoo-addon-stock-lot-product-qty-search
Version: 15.0.1.0.0.6
Summary: Allows to search on Quantity field of Lot/Serial Numbers
Home-page: https://github.com/OCA/stock-logistics-workflow
Author: Camptocamp, Odoo Community Association (OCA)
Author-email: support@odoo-community.org
License: AGPL-3
Platform: UNKNOWN
Classifier: Programming Language :: Python
Classifier: Framework :: Odoo
Classifier: Framework :: Odoo :: 15.0
Classifier: License :: OSI Approved :: GNU Affero General Public License v3
Classifier: Development Status :: 3 - Alpha
Requires-Python: >=3.8
Requires-Dist: odoo <15.1dev,>=15.0a
